LICENSE
MANIFEST.in
README.rst
config_example.json
setup.cfg
setup.py
signingworker/__init__.py
signingworker/consumer.py
signingworker/exceptions.py
signingworker/task.py
signingworker/utils.py
signingworker/worker.py
signingworker.egg-info/PKG-INFO
signingworker.egg-info/SOURCES.txt
signingworker.egg-info/dependency_links.txt
signingworker.egg-info/entry_points.txt
signingworker.egg-info/not-zip-safe
signingworker.egg-info/requires.txt
signingworker.egg-info/top_level.txt
signingworker/data/signing_task_schema.json
signingworker/test/__init__.py
signingworker/test/example_server_config.json
signingworker/test/id_rsa.pub
signingworker/test/test_load_signing_server_config.py
signingworker/test/test_task.py
signingworker/test/test_utils.py
signingworker/test/test_validate_task.py