Metadata-Version: 1.0
Name: signingworker
Version: 0.10
Summary: TaskCluster Signing Worker
Home-page: https://github.com/mozilla/signingworker
Author: Mozilla Release Engineering
Author-email: release+python@mozilla.com
License: MPL2
Platform: UNKNOWN
